bot/__init__.py
bot/filters/__init__.py
bot/handlers/__init__.py
bot/handlers/basic.py
bot/keyboards/__init__.py
bot/middlewares/__init__.py
core/__init__.py
core/config.py
botogram3-1.1.dist-info/METADATA
botogram3-1.1.dist-info/WHEEL
botogram3-1.1.dist-info/entry_points.txt
botogram3-1.1.dist-info/top_level.txt
botogram3-1.1.dist-info/RECORD
