Metadata-Version: 2.1
Name: botogram3
Version: 1.1
Summary: Botogram is a framework for AIOGRAM3
Author: Abraham
Author-email: abraha111.07@gmail.com
Classifier: License :: OSI Approved :: MIT License
Classifier: Programming Language :: Python :: 3
Classifier: Programming Language :: Python :: 3.10
Classifier: Programming Language :: Python :: 3.11
Requires-Dist: aiogram ==3.0.0b4
Requires-Dist: python-dotenv >=1.0.0
